{
	"configurations" : 
	[
		{
			"directories" : 
			[
				{
					"build" : ".",
					"hasInstallRule" : true,
					"jsonFile" : "directory-.-e0fa39b604182ebefda6.json",
					"minimumCMakeVersion" : 
					{
						"string" : "3.12"
					},
					"projectIndex" : 0,
					"source" : ".",
					"targetIndexes" : 
					[
						0,
						1,
						2,
						3,
						4
					]
				}
			],
			"name" : "",
			"projects" : 
			[
				{
					"directoryIndexes" : 
					[
						0
					],
					"name" : "arduinobot_utils",
					"targetIndexes" : 
					[
						0,
						1,
						2,
						3,
						4
					]
				}
			],
			"targets" : 
			[
				{
					"directoryIndex" : 0,
					"id" : "ament_cmake_python_build_arduinobot_utils_egg::@6890427a1f51a3e7e1df",
					"jsonFile" : "target-ament_cmake_python_build_arduinobot_utils_egg-b1e1fed2db4b4cb5faa1.json",
					"name" : "ament_cmake_python_build_arduinobot_utils_egg",
					"projectIndex" : 0
				},
				{
					"directoryIndex" : 0,
					"id" : "ament_cmake_python_copy_arduinobot_utils::@6890427a1f51a3e7e1df",
					"jsonFile" : "target-ament_cmake_python_copy_arduinobot_utils-c2d5d06d99e0b3a33985.json",
					"name" : "ament_cmake_python_copy_arduinobot_utils",
					"projectIndex" : 0
				},
				{
					"directoryIndex" : 0,
					"id" : "angle_conversion::@6890427a1f51a3e7e1df",
					"jsonFile" : "target-angle_conversion-3987c64665f381c1a66f.json",
					"name" : "angle_conversion",
					"projectIndex" : 0
				},
				{
					"directoryIndex" : 0,
					"id" : "arduinobot_utils_uninstall::@6890427a1f51a3e7e1df",
					"jsonFile" : "target-arduinobot_utils_uninstall-f52c80f7965a03b97a9a.json",
					"name" : "arduinobot_utils_uninstall",
					"projectIndex" : 0
				},
				{
					"directoryIndex" : 0,
					"id" : "uninstall::@6890427a1f51a3e7e1df",
					"jsonFile" : "target-uninstall-b87e894c92a3cc36d611.json",
					"name" : "uninstall",
					"projectIndex" : 0
				}
			]
		}
	],
	"kind" : "codemodel",
	"paths" : 
	{
		"build" : "/home/raz/projects/manipulator-project/Arduino-Bot/arduinobot_ws/build/arduinobot_utils",
		"source" : "/home/raz/projects/manipulator-project/Arduino-Bot/arduinobot_ws/src/arduinobot_utils"
	},
	"version" : 
	{
		"major" : 2,
		"minor" : 6
	}
}
